munzee/__init__.py
munzee/endpoint.py
munzee/endpoints/__init__.py
munzee/endpoints/clan.py
munzee/endpoints/map.py
munzee/endpoints/munzee.py
munzee/endpoints/player.py
munzee/endpoints/statzee.py
munzee/munzee.py
munzee-0.1.3.dist-info/LICENSE
munzee-0.1.3.dist-info/WHEEL
munzee-0.1.3.dist-info/METADATA
munzee-0.1.3.dist-info/RECORD
